pytest_telegram/__init__.py
pytest_telegram/plugin.py
pytest_telegram-1.2.1.dist-info/LICENSE
pytest_telegram-1.2.1.dist-info/METADATA
pytest_telegram-1.2.1.dist-info/WHEEL
pytest_telegram-1.2.1.dist-info/entry_points.txt
pytest_telegram-1.2.1.dist-info/top_level.txt
pytest_telegram-1.2.1.dist-info/RECORD
