Metadata-Version: 2.1
Name: pytest-telegram
Version: 1.2.1
Summary: Pytest to Telegram reporting plugin
Home-page: https://github.com/rad96/pytest-telegram
Author: Artem Ryabkov
Author-email: rad964@gmail.com
License: MIT license
Keywords: pytest,py.test,telegram
Classifier: Framework :: Pytest
Classifier: Development Status :: 5 - Production/Stable
Classifier: Intended Audience :: Developers
Classifier: License :: OSI Approved :: MIT License
Classifier: Natural Language :: English
Classifier: Programming Language :: Python :: 3.6
Classifier: Programming Language :: Python :: 3.7
Classifier: Programming Language :: Python :: 3.8
Classifier: Programming Language :: Python :: 3.9
License-File: LICENSE
Requires-Dist: requests
